ms_detect.py
ms_detect-0.0.1.dist-info/DESCRIPTION.rst
ms_detect-0.0.1.dist-info/METADATA
ms_detect-0.0.1.dist-info/RECORD
ms_detect-0.0.1.dist-info/WHEEL
ms_detect-0.0.1.dist-info/metadata.json
ms_detect-0.0.1.dist-info/top_level.txt
