Metadata-Version: 2.0
Name: ms-detect
Version: 0.0.1
Summary: micor soft detect
Home-page: http://www.zhaomingming.cn
Author: zhaomingming
Author-email: 13271929138@163.com
License: MIT
Platform: any
